twitter2eh.py
twitter2eh-0.2.0.dist-info/METADATA
twitter2eh-0.2.0.dist-info/RECORD
twitter2eh-0.2.0.dist-info/WHEEL
twitter2eh-0.2.0.dist-info/entry_points.txt
twitter2eh-0.2.0.dist-info/top_level.txt
