Metadata-Version: 2.1
Name: twitter2eh
Version: 0.2.0
Summary: Stream feed from Twitter to Azure Event Hub
Home-page: https://github.com/yokawasa/TwitterEventHubFeed
Author: Yoichi Kawasaki
Author-email: yoichi.kawasaki@microsoft.com
License: MIT
Download-URL: https://pypi.python.org/pypi/twitter2eh
Keywords: stream feed twitter azure eventhub
Platform: any
Classifier: Environment :: Console
Classifier: Intended Audience :: Developers
Classifier: Intended Audience :: System Administrators
Classifier: License :: OSI Approved :: MIT License
Classifier: Programming Language :: Python :: 3
Classifier: Programming Language :: Python :: 3.3
Classifier: Programming Language :: Python :: 3.4
Classifier: Programming Language :: Python :: 3.5
Classifier: Programming Language :: Python :: 3.6
Classifier: Topic :: Utilities
Requires-Dist: argparse
Requires-Dist: azure-servicebus
Requires-Dist: tweepy (==3.3.0)
